<annotation>
  <folder>VOC2007</folder>
  <filename>domain3/300204.jpg</filename>
  <segmented>0</segmented>
  <size>
    <width>487</width>
    <height>259</height>
    <depth>3</depth>
  </size>
  <object>
    <name>normal</name>
    <pose>Unspecified</pose>
    <truncated>0</truncated>
    <difficult>0</difficult>
    <bndbox>
      <xmin>190</xmin>
      <ymin>105</ymin>
      <xmax>381</xmax>
      <ymax>180</ymax>
    </bndbox>
  </object>
  <object>
    <name>normal</name>
    <pose>Unspecified</pose>
    <truncated>0</truncated>
    <difficult>0</difficult>
    <bndbox>
      <xmin>144</xmin>
      <ymin>96</ymin>
      <xmax>299</xmax>
      <ymax>181</ymax>
    </bndbox>
  </object>
  <object>
    <name>normal</name>
    <pose>Unspecified</pose>
    <truncated>0</truncated>
    <difficult>0</difficult>
    <bndbox>
      <xmin>89</xmin>
      <ymin>58</ymin>
      <xmax>324</xmax>
      <ymax>173</ymax>
    </bndbox>
  </object>
  <object>
    <name>pressure</name>
    <pose>Unspecified</pose>
    <truncated>0</truncated>
    <difficult>0</difficult>
    <bndbox>
      <xmin>395</xmin>
      <ymin>11</ymin>
      <xmax>483</xmax>
      <ymax>245</ymax>
    </bndbox>
  </object>
</annotation>
