<annotation>
  <folder>VOC2007</folder>
  <filename>domain2/200028.jpg</filename>
  <segmented>0</segmented>
  <size>
    <width>664</width>
    <height>456</height>
    <depth>3</depth>
  </size>
  <object>
    <name>normal</name>
    <pose>Unspecified</pose>
    <truncated>0</truncated>
    <difficult>0</difficult>
    <bndbox>
      <xmin>214</xmin>
      <ymin>157</ymin>
      <xmax>546</xmax>
      <ymax>361</ymax>
    </bndbox>
  </object>
  <object>
    <name>normal</name>
    <pose>Unspecified</pose>
    <truncated>0</truncated>
    <difficult>0</difficult>
    <bndbox>
      <xmin>197</xmin>
      <ymin>151</ymin>
      <xmax>373</xmax>
      <ymax>310</ymax>
    </bndbox>
  </object>
  <object>
    <name>normal</name>
    <pose>Unspecified</pose>
    <truncated>0</truncated>
    <difficult>0</difficult>
    <bndbox>
      <xmin>232</xmin>
      <ymin>174</ymin>
      <xmax>421</xmax>
      <ymax>364</ymax>
    </bndbox>
  </object>
  <object>
    <name>powerbank</name>
    <pose>Unspecified</pose>
    <truncated>0</truncated>
    <difficult>0</difficult>
    <bndbox>
      <xmin>219</xmin>
      <ymin>365</ymin>
      <xmax>373</xmax>
      <ymax>408</ymax>
    </bndbox>
  </object>
</annotation>
