<annotation>
  <folder>VOC2007</folder>
  <filename>domain1/100112.jpg</filename>
  <segmented>0</segmented>
  <size>
    <width>221</width>
    <height>197</height>
    <depth>3</depth>
  </size>
  <object>
    <name>normal</name>
    <pose>Unspecified</pose>
    <truncated>0</truncated>
    <difficult>0</difficult>
    <bndbox>
      <xmin>69</xmin>
      <ymin>67</ymin>
      <xmax>157</xmax>
      <ymax>125</ymax>
    </bndbox>
  </object>
  <object>
    <name>normal</name>
    <pose>Unspecified</pose>
    <truncated>0</truncated>
    <difficult>0</difficult>
    <bndbox>
      <xmin>77</xmin>
      <ymin>68</ymin>
      <xmax>136</xmax>
      <ymax>141</ymax>
    </bndbox>
  </object>
  <object>
    <name>lighter</name>
    <pose>Unspecified</pose>
    <truncated>0</truncated>
    <difficult>0</difficult>
    <bndbox>
      <xmin>165</xmin>
      <ymin>89</ymin>
      <xmax>193</xmax>
      <ymax>144</ymax>
    </bndbox>
  </object>
</annotation>
